omg/__init__.py
omg/colormap.py
omg/lineinfo.py
omg/lump.py
omg/mapedit.py
omg/palette.py
omg/playpal.py
omg/thinginfo.py
omg/txdef.py
omg/udmf.py
omg/util.py
omg/wad.py
omg/wadio.py
omgifol-0.5.1.data/scripts/drawmaps.py
omgifol-0.5.1.data/scripts/listdir.py
omgifol-0.5.1.data/scripts/merge.py
omgifol-0.5.1.data/scripts/mirror.py
omgifol-0.5.1.dist-info/LICENSE
omgifol-0.5.1.dist-info/METADATA
omgifol-0.5.1.dist-info/WHEEL
omgifol-0.5.1.dist-info/top_level.txt
omgifol-0.5.1.dist-info/RECORD
